mkdocs_strip_number_prefix/__init__.py
mkdocs_strip_number_prefix/plugin.py
vexy_mkdocs_strip_number_prefix-1.0.11.dist-info/METADATA
vexy_mkdocs_strip_number_prefix-1.0.11.dist-info/WHEEL
vexy_mkdocs_strip_number_prefix-1.0.11.dist-info/entry_points.txt
vexy_mkdocs_strip_number_prefix-1.0.11.dist-info/licenses/LICENSE
vexy_mkdocs_strip_number_prefix-1.0.11.dist-info/RECORD
