Metadata-Version: 2.4
Name: vexy-mkdocs-strip-number-prefix
Version: 1.0.11
Summary: MkDocs plugin to strip numeric prefixes from page URLs while keeping them in source files
Project-URL: Homepage, https://github.com/vexyart/vexy-mkdocs-strip-number-prefix
Project-URL: Documentation, https://github.com/vexyart/vexy-mkdocs-strip-number-prefix
Project-URL: Repository, https://github.com/vexyart/vexy-mkdocs-strip-number-prefix
Project-URL: Issues, https://github.com/vexyart/vexy-mkdocs-strip-number-prefix/issues
Project-URL: Changelog, https://github.com/vexyart/vexy-mkdocs-strip-number-prefix/blob/main/CHANGELOG.md
Author-email: Vexy Lines Team <help@vexy.art>
Maintainer-email: Vexy Lines Team <help@vexy.art>
License: MIT
License-File: LICENSE
Keywords: documentation,mkdocs,numbering,plugin,prefix,slug,url
Classifier: Development Status :: 4 - Beta
Classifier: Framework :: MkDocs
Classifier: Intended Audience :: Developers
Classifier: License :: OSI Approved :: MIT License
Classifier: Operating System :: OS Independent
Classifier: Programming Language :: Python :: 3
Classifier: Programming Language :: Python :: 3.9
Classifier: Programming Language :: Python :: 3.10
Classifier: Programming Language :: Python :: 3.11
Classifier: Programming Language :: Python :: 3.12
Classifier: Topic :: Documentation
Classifier: Topic :: Software Development :: Documentation
Classifier: Topic :: Text Processing
Requires-Python: >=3.9
Requires-Dist: mkdocs>=1.5.0
Provides-Extra: dev
Requires-Dist: black>=23.7.0; extra == 'dev'
Requires-Dist: mypy>=1.5.0; extra == 'dev'
Requires-Dist: pre-commit>=3.3.0; extra == 'dev'
Requires-Dist: pytest-cov>=4.1.0; extra == 'dev'
Requires-Dist: pytest-mock>=3.11.0; extra == 'dev'
Requires-Dist: pytest>=7.4.0; extra == 'dev'
Requires-Dist: ruff>=0.1.0; extra == 'dev'
Provides-Extra: docs
Requires-Dist: mkdocstrings[python]>=0.24.0; extra == 'docs'
Requires-Dist: vexy-mkdocs-awesome-nav>=1.2.2; extra == 'docs'
Requires-Dist: vexy-mkdocs-material>=9.4.0; extra == 'docs'
